odoo/addons/helm_import/LICENSE
odoo/addons/helm_import/README.rst
odoo/addons/helm_import/__init__.py
odoo/addons/helm_import/__manifest__.py
odoo/addons/helm_import/images/screen.png
odoo/addons/helm_import/models/__init__.py
odoo/addons/helm_import/models/helm_repo.py
odoo/addons/helm_import/static/description/icon.png
odoo/addons/helm_import/static/description/index.html
odoo/addons/helm_import/views/helm_repo_views.xml
odoo_addon_helm_import-18.0.1.0.0.dist-info/METADATA
odoo_addon_helm_import-18.0.1.0.0.dist-info/WHEEL
odoo_addon_helm_import-18.0.1.0.0.dist-info/top_level.txt
odoo_addon_helm_import-18.0.1.0.0.dist-info/RECORD
